setup.py
analyzers/__init__.py
analyzers.egg-info/PKG-INFO
analyzers.egg-info/SOURCES.txt
analyzers.egg-info/dependency_links.txt
analyzers.egg-info/not-zip-safe
analyzers.egg-info/top_level.txt