Metadata-Version: 1.0
Name: analyzers
Version: 0.1.1
Summary: Analysers for elasticsearch for best suggestion and auto complete
Home-page: https://github.com/Poorvak/analyzers
Author: Poorvak Kapoor
Author-email: poorvak.kapoor@gmail.com
License: MIT
Platform: UNKNOWN
